<document>

    <properties>
        <author email="kit@objectlab.co.uk">Benoit Xhenseval</author>
        <title>Code Metrics</title>
    </properties>

    <head>
        <meta name="description"
            content="ObjectLab Kit offers free and open source Date calculators, released under the business-friendly Apache 2.0 license." />
        <meta name="keywords" content="Date calculator, IMM Dates, Period Calculator, Financial Calendar, Business Calendar, java, open source" />
        <meta name="Subject" content="Date Calculators" />
        <meta name="Copyright" content="ObjectLab Financial Ltd" />
        <meta name="Language" content="English" />
        <meta name="Designer" content="ObjectLab Financial Ltd" />
        <meta name="Distribution" content="Global" />
        <meta name="robots" content="ALL" />
        <meta name="Revisit-After" content="20 Days" />
    </head>

    <body>

        <subsection name="Code Metrics">
            <div id="sonar">
                <a href="https://sonarcloud.io/dashboard/index/net.objectlab.kit:kit-parent">
                    <span>
                        <img src="https://sonarcloud.io/api/project_badges/quality_gate?project=net.objectlab.kit:kit-parent" />
                    </span>
                    <span>
                        View Code Metrics by Sonar
                    </span>
                </a>
            </div>
        </subsection>

        <subsection name="Ohloh Stats">
            <div id="ohloh">
                <div id="cocomo">
                    <script type="text/javascript" src="http://www.ohloh.net/p/4682/widgets/project_cocomo.js"></script>
                </div>
                <div id="factoids">
                    <script type="text/javascript" src="http://www.ohloh.net/p/4682/widgets/project_factoids_stats.js"></script>
                </div>
                <div id="iuseit">
                    <script type="text/javascript" src="http://www.ohloh.net/p/4682/widgets/project_users.js?style=green"></script>
                </div>
            </div>
        </subsection>

    </body>

</document>